hello_test_rinki/__init__.py
hello_test_rinki/__main__.py
hello_test_rinki-1.0.3.dist-info/METADATA
hello_test_rinki-1.0.3.dist-info/WHEEL
hello_test_rinki-1.0.3.dist-info/top_level.txt
hello_test_rinki-1.0.3.dist-info/RECORD
